altron/__init__.py
altron/robot.py
altron-0.0.2.dist-info/LICENSE
altron-0.0.2.dist-info/METADATA
altron-0.0.2.dist-info/WHEEL
altron-0.0.2.dist-info/top_level.txt
altron-0.0.2.dist-info/RECORD
