Metadata-Version: 2.1
Name: altron
Version: 0.0.2
Summary: TheAltron
Author: Axen
Author-email: thexboy131@gmail.com
Keywords: python,pyrogram,altron
Classifier: Development Status :: 1 - Planning
Classifier: Programming Language :: Python :: 3
Classifier: Operating System :: Unix
Classifier: Operating System :: MacOS :: MacOS X
Classifier: Operating System :: Microsoft :: Windows
License-File: LICENSE
Requires-Dist: pyrogram (==1.4.16)
Requires-Dist: TgCrypto
